tytest/__init__.py
tytest/exceptions.py
tytest/plugin.py
tytest/runtime_settings.py
tytest/utils.py
tytest/xray_api.py
pytest_typhoon_xray-0.1.16.dist-info/LICENSE
pytest_typhoon_xray-0.1.16.dist-info/METADATA
pytest_typhoon_xray-0.1.16.dist-info/WHEEL
pytest_typhoon_xray-0.1.16.dist-info/entry_points.txt
pytest_typhoon_xray-0.1.16.dist-info/top_level.txt
pytest_typhoon_xray-0.1.16.dist-info/RECORD
