Metadata-Version: 2.1
Name: pytest-typhoon-xray
Version: 0.1.16
Summary: Typhoon HIL plugin for pytest
Home-page: https://github.com/typhoon-hil/pytest-typhoon-xray
Author: Branko Milosavljevic
Author-email: branko@typhoon-hil.com
Maintainer: Branko Milosavljevic
Maintainer-email: branko@typhoon-hil.com
License: MIT
Platform: UNKNOWN
Classifier: Development Status :: 4 - Beta
Classifier: Framework :: Pytest
Classifier: Intended Audience :: Developers
Classifier: Topic :: Software Development :: Testing
Classifier: Programming Language :: Python
Classifier: Programming Language :: Python :: 3
Classifier: Programming Language :: Python :: 3.6
Classifier: Programming Language :: Python :: 3.7
Classifier: Programming Language :: Python :: Implementation :: CPython
Classifier: Operating System :: OS Independent
Classifier: License :: OSI Approved :: MIT License
Requires-Python: >=3.6
Requires-Dist: pytest (>=5.4.2)
Requires-Dist: pytz (>=2020.1)
Requires-Dist: tzlocal (>=2.1)
Requires-Dist: requests (>=2.23)
